sagemaker_datawrangler/__init__.py
sagemaker_datawrangler/_frontend.py
sagemaker_datawrangler/_version.py
sagemaker_datawrangler/datawrangler.py
sagemaker_datawrangler/config/__init__.py
sagemaker_datawrangler/config/compute_scale_checkbox.py
sagemaker_datawrangler/config/config.py
sagemaker_datawrangler/config/ipython_display.py
sagemaker_datawrangler/config/toggle_widget.py
sagemaker_datawrangler/datatable/__init__.py
sagemaker_datawrangler/datatable/df_converter.py
sagemaker_datawrangler/datatable/df_sort.py
sagemaker_datawrangler/insights/__init__.py
sagemaker_datawrangler/insights/column_insights.py
sagemaker_datawrangler/insights/data_quality_insights.py
sagemaker_datawrangler/insights/feature_column_insights_schema.py
sagemaker_datawrangler/insights/insights_constants.py
sagemaker_datawrangler/insights/parser.py
sagemaker_datawrangler/insights/target_column_insights.py
sagemaker_datawrangler/insights/target_column_insights_schema.py
sagemaker_datawrangler/insights/utils.py
sagemaker_datawrangler/labextension/package.json
sagemaker_datawrangler/labextension/static/152.3573a4761768372b28ac.js
sagemaker_datawrangler/labextension/static/152.3573a4761768372b28ac.js.LICENSE.txt
sagemaker_datawrangler/labextension/static/194.4646126886b1ec0c026b.js
sagemaker_datawrangler/labextension/static/251.4a3844a0b1c7cfb32c85.js
sagemaker_datawrangler/labextension/static/251.4a3844a0b1c7cfb32c85.js.LICENSE.txt
sagemaker_datawrangler/labextension/static/283.a22c2607dd3fa03b65bc.js
sagemaker_datawrangler/labextension/static/283.a22c2607dd3fa03b65bc.js.LICENSE.txt
sagemaker_datawrangler/labextension/static/295.02122c1766846ea6ae30.js
sagemaker_datawrangler/labextension/static/295.02122c1766846ea6ae30.js.LICENSE.txt
sagemaker_datawrangler/labextension/static/320.b592e82a27be61c378a6.js
sagemaker_datawrangler/labextension/static/346.3416f1bab73ec2736001.js
sagemaker_datawrangler/labextension/static/367.bbc4e7dca7ace78e6905.js
sagemaker_datawrangler-0.4.3.dist-info/METADATA
sagemaker_datawrangler-0.4.3.dist-info/WHEEL
sagemaker_datawrangler-0.4.3.dist-info/top_level.txt
sagemaker_datawrangler-0.4.3.dist-info/RECORD
