Metadata-Version: 2.1
Name: sagemaker-datawrangler
Version: 0.4.3
Summary: Amazon SageMaker Data Wrangler Library
Home-page: 
License: AWS Customer Agreement
Keywords: Python
Platform: Linux
Platform: Mac OS X
Platform: Windows
Classifier: Programming Language :: Python
Classifier: Programming Language :: Python :: 3
Classifier: Programming Language :: Python :: 3.7
Classifier: Programming Language :: Python :: 3.8
Classifier: Programming Language :: Python :: 3.9
Classifier: Programming Language :: Python :: 3.10
Requires-Python: >=3.7
Requires-Dist: sagemaker-data-insights (==0.4.0)
Requires-Dist: ipywidgets (<8.0.0)
